bmpf.py
bmpf-0.0.2.dist-info/LICENSE
bmpf-0.0.2.dist-info/METADATA
bmpf-0.0.2.dist-info/WHEEL
bmpf-0.0.2.dist-info/top_level.txt
bmpf-0.0.2.dist-info/RECORD
