Metadata-Version: 2.1
Name: bmpf
Version: 0.0.2
Summary: Basic multi-period featurizer.
Home-page: UNKNOWN
Author: Enzo Busseti
Author-email: UNKNOWN
License: Apache 2.0
Platform: UNKNOWN
Requires-Dist: numpy (>=1.17.3)
Requires-Dist: pandas (>=0.25.3)
